pytest_involve.py
pytest_involve-0.1.4.dist-info/LICENSE
pytest_involve-0.1.4.dist-info/METADATA
pytest_involve-0.1.4.dist-info/WHEEL
pytest_involve-0.1.4.dist-info/entry_points.txt
pytest_involve-0.1.4.dist-info/top_level.txt
pytest_involve-0.1.4.dist-info/RECORD
