Metadata-Version: 2.1
Name: pytest-involve
Version: 0.1.4
Summary: Run tests covering a specific file or changeset
Home-page: https://github.com/MisterKeefe/pytest-involve
Author: Tom Keefe
Author-email: tomlkeefe@gmail.com
Maintainer: Tom Keefe
Maintainer-email: tomlkeefe@gmail.com
License: MIT
Platform: UNKNOWN
Classifier: Development Status :: 4 - Beta
Classifier: Framework :: Pytest
Classifier: Intended Audience :: Developers
Classifier: Topic :: Software Development :: Testing
Classifier: Programming Language :: Python
Classifier: Programming Language :: Python :: 3
Classifier: Programming Language :: Python :: 3.6
Classifier: Programming Language :: Python :: 3.7
Classifier: Programming Language :: Python :: 3.8
Classifier: Programming Language :: Python :: Implementation :: CPython
Classifier: Operating System :: OS Independent
Classifier: License :: OSI Approved :: MIT License
Requires-Python: >=3.6
Requires-Dist: pytest (>=3.5.0)
